cloud_storage_service/__init__.py
cloud_storage_service/aws_storage.py
cloud_storage_service/azure_storage.py
cloud_storage_service/gcp_storage.py
cloud_storage_service/storage_manager.py
cloud_storage_service-0.2.42.dist-info/LICENSE
cloud_storage_service-0.2.42.dist-info/METADATA
cloud_storage_service-0.2.42.dist-info/WHEEL
cloud_storage_service-0.2.42.dist-info/top_level.txt
cloud_storage_service-0.2.42.dist-info/RECORD
