Metadata-Version: 2.2
Name: cloud_storage_service
Version: 0.2.42
Summary: A unified cloud storage package for AWS, Azure, and GCP
Author: Aaditya Muleva, Vinay Shankar Miryala
Author-email: aaditya.muleva@trovehealth.io, vinay.miryala@trovehealth.io
License: MIT
Classifier: Programming Language :: Python :: 3
Classifier: License :: OSI Approved :: MIT License
Classifier: Operating System :: OS Independent
Classifier: Development Status :: 5 - Production/Stable
Classifier: Intended Audience :: Developers
Classifier: Topic :: Software Development :: Libraries :: Python Modules
Requires-Python: >=3.6
License-File: LICENSE
Requires-Dist: pandas
Requires-Dist: awswrangler
Requires-Dist: azure-storage-blob
Requires-Dist: google-cloud-storage
Requires-Dist: google-api-core
Requires-Dist: openpyxl
Requires-Dist: xlsxwriter
Dynamic: author
Dynamic: author-email
Dynamic: classifier
Dynamic: description
Dynamic: description-content-type
Dynamic: license
Dynamic: requires-dist
Dynamic: requires-python
Dynamic: summary
